README.txt
setup.py
deadlock/__init__.py
deadlock/core.py
deadlock/crypto.py
deadlock.egg-info/PKG-INFO
deadlock.egg-info/SOURCES.txt
deadlock.egg-info/dependency_links.txt
deadlock.egg-info/entry_points.txt
deadlock.egg-info/requires.txt
deadlock.egg-info/top_level.txt
deadlock/crypto_fallbacks/__init__.py
deadlock/crypto_fallbacks/blake2.py
deadlock/passwords/__init__.py
deadlock/passwords/phrase.py
deadlock/passwords/wordlist.py
deadlock/passwords/zxcvbn/__init__.py
deadlock/passwords/zxcvbn/main.py
deadlock/passwords/zxcvbn/matching.py
deadlock/passwords/zxcvbn/scoring.py
deadlock/passwords/zxcvbn/data/README
deadlock/passwords/zxcvbn/data/common_passwords.txt
deadlock/passwords/zxcvbn/data/tv_and_movie_freqlist1-1000.html
deadlock/passwords/zxcvbn/data/tv_and_movie_freqlist10001-12000.html
deadlock/passwords/zxcvbn/data/tv_and_movie_freqlist1001-2000.html
deadlock/passwords/zxcvbn/data/tv_and_movie_freqlist12001-14000.html
deadlock/passwords/zxcvbn/data/tv_and_movie_freqlist14001-16000.html
deadlock/passwords/zxcvbn/data/tv_and_movie_freqlist16001-18000.html
deadlock/passwords/zxcvbn/data/tv_and_movie_freqlist18001-20000.html
deadlock/passwords/zxcvbn/data/tv_and_movie_freqlist20001-22000.html
deadlock/passwords/zxcvbn/data/tv_and_movie_freqlist2001-3000.html
deadlock/passwords/zxcvbn/data/tv_and_movie_freqlist22001-24000.html
deadlock/passwords/zxcvbn/data/tv_and_movie_freqlist24001-26000.html
deadlock/passwords/zxcvbn/data/tv_and_movie_freqlist26001-28000.html
deadlock/passwords/zxcvbn/data/tv_and_movie_freqlist28001-30000.html
deadlock/passwords/zxcvbn/data/tv_and_movie_freqlist30001-32000.html
deadlock/passwords/zxcvbn/data/tv_and_movie_freqlist3001-4000.html
deadlock/passwords/zxcvbn/data/tv_and_movie_freqlist32001-34000.html
deadlock/passwords/zxcvbn/data/tv_and_movie_freqlist34001-36000.html
deadlock/passwords/zxcvbn/data/tv_and_movie_freqlist36001-38000.html
deadlock/passwords/zxcvbn/data/tv_and_movie_freqlist38001-40000.html
deadlock/passwords/zxcvbn/data/tv_and_movie_freqlist40001-41284.html
deadlock/passwords/zxcvbn/data/tv_and_movie_freqlist4001-5000.html
deadlock/passwords/zxcvbn/data/tv_and_movie_freqlist5001-6000.html
